trulens/_mods.py
trulens/apps/app.py
trulens/apps/basic.py
trulens/apps/custom.py
trulens/apps/py.typed
trulens/apps/virtual.py
trulens/core/__init__.py
trulens/core/_utils/debug.py
trulens/core/_utils/optional.py
trulens/core/_utils/pycompat.py
trulens/core/app.py
trulens/core/database/__init__.py
trulens/core/database/base.py
trulens/core/database/connector/__init__.py
trulens/core/database/connector/base.py
trulens/core/database/connector/default.py
trulens/core/database/exceptions.py
trulens/core/database/legacy/__init__.py
trulens/core/database/legacy/migration.py
trulens/core/database/migrations/__init__.py
trulens/core/database/migrations/alembic.ini
trulens/core/database/migrations/data.py
trulens/core/database/migrations/env.py
trulens/core/database/migrations/script.py.mako
trulens/core/database/migrations/versions/10_create_event_table.py
trulens/core/database/migrations/versions/1_first_revision.py
trulens/core/database/migrations/versions/2_add_run_location_column_to_feedback_defs_table.py
trulens/core/database/migrations/versions/3_add_groundtruth_and_dataset_tables.py
trulens/core/database/migrations/versions/4_set_ff_id_not_null.py
trulens/core/database/migrations/versions/5_add_app_name_and_version_fields.py
trulens/core/database/migrations/versions/6_populate_app_name_and_version_data.py
trulens/core/database/migrations/versions/7_app_name_version_not_null.py
trulens/core/database/migrations/versions/8_update_records_app_id.py
trulens/core/database/migrations/versions/9_update_app_json.py
trulens/core/database/orm.py
trulens/core/database/sqlalchemy.py
trulens/core/database/utils.py
trulens/core/enums.py
trulens/core/experimental/__init__.py
trulens/core/feedback/__init__.py
trulens/core/feedback/custom_metric.py
trulens/core/feedback/endpoint.py
trulens/core/feedback/feedback.py
trulens/core/feedback/feedback_function_input.py
trulens/core/feedback/provider.py
trulens/core/feedback/selector.py
trulens/core/guardrails/__init__.py
trulens_core-2.5.0.dist-info/METADATA
trulens_core-2.5.0.dist-info/WHEEL
trulens_core-2.5.0.dist-info/RECORD
